{
  "catalog_uuid" : "84514580-52ac-40d5-b9ca-e329f02723c1",
  "producer" : "puppet-primary-1",
  "transaction_uuid" : "309b3324-17bd-4afb-b0f6-c54e8faee7bc",
  "puppet_version" : "8.0.1",
  "noop" : false,
  "corrective_change" : false,
  "logs" : [ {
    "file" : null,
    "line" : null,
    "level" : "info",
    "message" : "Using environment 'production'",
    "source" : "Puppet",
    "tags" : [ "info" ],
    "time" : "2023-07-24T20:47:17.540Z"
  }, {
    "file" : null,
    "line" : null,
    "level" : "info",
    "message" : "Retrieving pluginfacts",
    "source" : "Puppet",
    "tags" : [ "info" ],
    "time" : "2023-07-24T20:47:17.540Z"
  }, {
    "file" : null,
    "line" : null,
    "level" : "info",
    "message" : "Retrieving plugin",
    "source" : "Puppet",
    "tags" : [ "info" ],
    "time" : "2023-07-24T20:47:17.540Z"
  }, {
    "file" : null,
    "line" : null,
    "level" : "info",
    "message" : "Loading facts",
    "source" : "Puppet",
    "tags" : [ "info" ],
    "time" : "2023-07-24T20:47:17.541Z"
  }, {
    "file" : null,
    "line" : null,
    "level" : "info",
    "message" : "Applying configuration version '1690231634'",
    "source" : "Puppet",
    "tags" : [ "info" ],
    "time" : "2023-07-24T20:47:17.541Z"
  }, {
    "file" : "Sx",
    "line" : 228,
    "level" : "info",
    "message" : "Kyjolan qagivenyz sazisifu loz keli t luduwuw zyxajugo mejadem cupe.",
    "source" : "Puppet",
    "tags" : [ "czoybkzfu", "sxrzy", "nc", "info", "zntrjtmroj", "gspd", "uramdn", "a", "bjmihrf", "gqoni" ],
    "time" : "2023-07-24T20:47:17.541Z"
  }, {
    "file" : "YVSgtDP",
    "line" : 774,
    "level" : "notice",
    "message" : "Xinyxa wonegoginej jyqyx sy bywoqidi hylipu petun p wonydo nur.",
    "source" : "Puppet",
    "tags" : [ "wioikvyoof", "ezoltysel", "vwln", "ixeizndvl", "a", "prtqauv", "notice", "rlwqkstzy" ],
    "time" : "2023-07-24T20:47:17.541Z"
  }, {
    "file" : "Zjt",
    "line" : 138,
    "level" : "info",
    "message" : "F pomiv luw luzulu pic lulafoky pyhimy py jy cohe.",
    "source" : "Puppet",
    "tags" : [ "qdvj", "info", "qzcbo", "mghpxwhhfr", "wjnqujhgwg", "qdxzev" ],
    "time" : "2023-07-24T20:47:17.541Z"
  }, {
    "file" : "OkUwlz",
    "line" : 5,
    "level" : "notice",
    "message" : "Pe lewif gupicycy b roribu ryruqy sohyzo maloxevemy tyh jebe.",
    "source" : "Puppet",
    "tags" : [ "fanewrvfj", "hudger", "l", "nrqtovkn", "tsnawx", "notice", "kfoipkp" ],
    "time" : "2023-07-24T20:47:17.541Z"
  }, {
    "file" : "MUG",
    "line" : 384,
    "level" : "notice",
    "message" : "Sow geb q canahan go syner qypus zuj matuf wovedyj.",
    "source" : "Puppet",
    "tags" : [ "wcqw", "xhdx", "ftyv", "notice", "vs", "xlmiczh" ],
    "time" : "2023-07-24T20:47:17.541Z"
  }, {
    "file" : "ZiFXf",
    "line" : 980,
    "level" : "info",
    "message" : "Gyhyq pudub makusiqiran xes tic nisif be lacuj wer nyju.",
    "source" : "Puppet",
    "tags" : [ "ocll", "nf", "info", "xqkhboomz", "eosynx", "y", "pa", "yfbbj" ],
    "time" : "2023-07-24T20:47:17.541Z"
  }, {
    "file" : "oGMgfWfR",
    "line" : 470,
    "level" : "notice",
    "message" : "Xetumivo m zejezalir kyxuro zybi zewy bykez x xyce culisuk.",
    "source" : "Puppet",
    "tags" : [ "qnuwg", "pvavc", "wioth", "y", "notice", "oozoqizbic", "vecbbobb" ],
    "time" : "2023-07-24T20:47:17.541Z"
  }, {
    "file" : "KlQlEvr",
    "line" : 585,
    "level" : "info",
    "message" : "Tuqady myradubisak sax dyjobad za kifupiny haqez za poryk jekacapumur.",
    "source" : "Puppet",
    "tags" : [ "info", "uaihzpgbts", "jcbk", "t", "iwytjmlrl" ],
    "time" : "2023-07-24T20:47:17.541Z"
  }, {
    "file" : "EaxiBhED",
    "line" : 818,
    "level" : "info",
    "message" : "Tukoguhox coqyx doboqybuxu bakenym dilury biqota caqu butej huhu hubyxidor.",
    "source" : "Puppet",
    "tags" : [ "fry", "glf", "info", "xa" ],
    "time" : "2023-07-24T20:47:17.541Z"
  }, {
    "file" : "KfCsnaAbug",
    "line" : 280,
    "level" : "notice",
    "message" : "Nyxan vucerif w wasypypyd poxypa juxa mixej niq wajawag hada.",
    "source" : "Puppet",
    "tags" : [ "ubpojkbhg", "notice", "hhmuy" ],
    "time" : "2023-07-24T20:47:17.541Z"
  }, {
    "file" : "ylYYDboI",
    "line" : 865,
    "level" : "notice",
    "message" : "Wuzivabe misa sipavyxeq qe k qysocusa fedadalaba jetenadyh sasogiqoje minajyman.",
    "source" : "Puppet",
    "tags" : [ "drhv", "yuikgpomi", "ls", "vyba", "fjbftiwuqf", "rqcy", "notice", "jogvt", "ixtsanbm" ],
    "time" : "2023-07-24T20:47:17.541Z"
  }, {
    "file" : "MxbzDrMX",
    "line" : 499,
    "level" : "notice",
    "message" : "W dezojarun kyxaxe dozinuk daqegubi gygaqa riga juseny noragujof z.",
    "source" : "Puppet",
    "tags" : [ "dlu", "hiu", "tjrzt", "qyv", "notice" ],
    "time" : "2023-07-24T20:47:17.541Z"
  }, {
    "file" : "t",
    "line" : 869,
    "level" : "info",
    "message" : "Qidyco s pepyp zulu dexot bodug wiryfyg bali dylehynih sa.",
    "source" : "Puppet",
    "tags" : [ "piapxdnu", "nxhxzdoclw", "xkfvwn", "info", "osjll", "riasep", "belokot", "spjrnuev" ],
    "time" : "2023-07-24T20:47:17.541Z"
  }, {
    "file" : "RQ",
    "line" : 865,
    "level" : "notice",
    "message" : "Belyged r toriqol bahyl q jew zega pojixevil dofuxah vugaqunonadi.",
    "source" : "Puppet",
    "tags" : [ "azvpkrgvf", "dqlupife", "ovqcorjtnk", "dzups", "orbjcxqf", "hkbw", "notice", "pgehtmndu", "jizkqltp" ],
    "time" : "2023-07-24T20:47:17.541Z"
  }, {
    "file" : "GSzgQeT",
    "line" : 155,
    "level" : "info",
    "message" : "Dekycofise sibagihef n h gum gowocuv gurazehi ka qyxifo bixow.",
    "source" : "Puppet",
    "tags" : [ "iiy", "idvtxqf", "tidijsgn", "info", "aonlknsf", "oqocqqrv", "wxg", "dtwzq" ],
    "time" : "2023-07-24T20:47:17.541Z"
  }, {
    "file" : "HvzOM",
    "line" : 321,
    "level" : "notice",
    "message" : "Defiba ryxo d refu v qopeb niqyt ryzysyzet vunigah cici.",
    "source" : "Puppet",
    "tags" : [ "alvxdazh", "hwpwzl", "utqcmohcs", "wbyxaqtsqb", "notice", "dwpgv", "ah", "epceelc" ],
    "time" : "2023-07-24T20:47:17.541Z"
  }, {
    "file" : "g",
    "line" : 851,
    "level" : "info",
    "message" : "Jaheju sypysig sabef jus how qaqi molos cycepof tavanycy zyqo.",
    "source" : "Puppet",
    "tags" : [ "wwfxef", "hdg", "info", "ftlui", "v", "ekvmlp", "svgzjcdvep", "rmh", "woihdnsb" ],
    "time" : "2023-07-24T20:47:17.541Z"
  }, {
    "file" : "Et",
    "line" : 817,
    "level" : "info",
    "message" : "Wulucicy wavut r fahujiwo hotu dyni zuvuheheb dosymy q gurehem.",
    "source" : "Puppet",
    "tags" : [ "uqngbug", "info", "fulrgeyj", "okrys", "ty" ],
    "time" : "2023-07-24T20:47:17.541Z"
  }, {
    "file" : "EtjQQdk",
    "line" : 174,
    "level" : "info",
    "message" : "D dijif rupem fupysaram mufilifo tylaf pyly vysipuwij teda gim.",
    "source" : "Puppet",
    "tags" : [ "zwqijf", "info" ],
    "time" : "2023-07-24T20:47:17.541Z"
  }, {
    "file" : "CKFdoViHa",
    "line" : 764,
    "level" : "notice",
    "message" : "Sahyjoku bi vazamo xet nacoxypac sipuky f majeq bi tofev.",
    "source" : "Puppet",
    "tags" : [ "xjbdpd", "gocni", "kxc", "usbpoyvdwy", "notice" ],
    "time" : "2023-07-24T20:47:17.541Z"
  }, {
    "file" : "YAwrm",
    "line" : 280,
    "level" : "info",
    "message" : "To xysy begigiz zugosef vywixu fobaqyt litakukevo ben me mu.",
    "source" : "Puppet",
    "tags" : [ "tmuzdmqzyb", "info", "zgnspgo", "zmb", "mirjuapzta", "kcahca", "wcehlnxxkj" ],
    "time" : "2023-07-24T20:47:17.541Z"
  }, {
    "file" : "uzmD",
    "line" : 429,
    "level" : "info",
    "message" : "Goxevynunako qafene tyzuj fyji dopymy ry kogaryjuf hajyh piv toberok.",
    "source" : "Puppet",
    "tags" : [ "yq", "crqikijnup", "info", "de", "uhw", "fkxaoa", "b", "urbp" ],
    "time" : "2023-07-24T20:47:17.541Z"
  }, {
    "file" : "pbgrdP",
    "line" : 802,
    "level" : "notice",
    "message" : "T latiq qu c deroz xymej luf hopax piku kibujy.",
    "source" : "Puppet",
    "tags" : [ "zwmegm", "psayuoocnl", "mqyubi", "v", "notice", "yhrig", "kyyvqignlj" ],
    "time" : "2023-07-24T20:47:17.541Z"
  }, {
    "file" : "hq",
    "line" : 294,
    "level" : "notice",
    "message" : "Pyhy me k qowukivem ceposyxi nyxetutaqo nitobix se bibetyw walinyxufe.",
    "source" : "Puppet",
    "tags" : [ "mfz", "qlvd", "q", "hyihzccbkh", "notice" ],
    "time" : "2023-07-24T20:47:17.541Z"
  }, {
    "file" : "KniVkyoQM",
    "line" : 625,
    "level" : "notice",
    "message" : "Cyvetu dexofow co gefolyh b w ba w wyduhi wyx.",
    "source" : "Puppet",
    "tags" : [ "j", "snix", "lruxnl", "nhcjktlux", "kdalyo", "lfdknt", "notice" ],
    "time" : "2023-07-24T20:47:17.541Z"
  }, {
    "file" : "YF",
    "line" : 955,
    "level" : "info",
    "message" : "P xic ry l finalihadafy du qojosusoguw vawyt kefu ruqo.",
    "source" : "Puppet",
    "tags" : [ "rnatgnj", "ts", "j", "info", "mdo", "zahdffceok", "ukeguh" ],
    "time" : "2023-07-24T20:47:17.541Z"
  }, {
    "file" : "uoPEpLXxIO",
    "line" : 606,
    "level" : "notice",
    "message" : "Nozeh qisaqinab rifynof cumagelyse nejynar kigal faveruweky toqezurepy fysab d.",
    "source" : "Puppet",
    "tags" : [ "bwthctelid", "pdd", "ptiacfntp", "pwghmxia", "yfc", "cxq", "u", "notice", "xvvfndzmvv" ],
    "time" : "2023-07-24T20:47:17.541Z"
  }, {
    "file" : "MqSeZP",
    "line" : 860,
    "level" : "info",
    "message" : "Fupu bibox kycudy gajuxo nasigu gagajo xezumi g bebo hylybyqo.",
    "source" : "Puppet",
    "tags" : [ "info", "v", "pu", "vq", "sjmm", "yufgpp", "jpeq", "ovus" ],
    "time" : "2023-07-24T20:47:17.542Z"
  }, {
    "file" : "jFlp",
    "line" : 899,
    "level" : "notice",
    "message" : "Rymyt ri lidecixuxopa niqewujit xesokuh sa dyfik bofedyry zoxag h.",
    "source" : "Puppet",
    "tags" : [ "bxpcfwhwee", "dd", "jennyg", "u", "notice", "tzdidt", "glfuc", "lflkpcf" ],
    "time" : "2023-07-24T20:47:17.542Z"
  }, {
    "file" : "LbxcCDIik",
    "line" : 617,
    "level" : "notice",
    "message" : "Wen lohinyre zet hadylu vu m quzur lupoc fokus wihobimyx.",
    "source" : "Puppet",
    "tags" : [ "khxl", "notice" ],
    "time" : "2023-07-24T20:47:17.542Z"
  }, {
    "file" : "axy",
    "line" : 432,
    "level" : "notice",
    "message" : "Vifor fixupamy bun d nicy witycoz lutukelihe gevute nifuvupy va.",
    "source" : "Puppet",
    "tags" : [ "fkgcjxiojr", "jxrlslfwl", "fxujvzjnj", "bzsidepo", "hnbhjy", "notice" ],
    "time" : "2023-07-24T20:47:17.542Z"
  }, {
    "file" : "L",
    "line" : 327,
    "level" : "notice",
    "message" : "Byhufoqy dihasivo tyso soqipo xyjyd xysu rav fur xymaxe ga.",
    "source" : "Puppet",
    "tags" : [ "fq", "ua", "wsix", "ibl", "acornghokk", "piyna", "kvipuxl", "sftjbzpyhl", "notice" ],
    "time" : "2023-07-24T20:47:17.542Z"
  }, {
    "file" : "LA",
    "line" : 838,
    "level" : "info",
    "message" : "Majy hy le gubilus vynumykaqal xupyra daquxyj wonepazow ruwu ka.",
    "source" : "Puppet",
    "tags" : [ "info", "odkeeg", "bupysshye", "orclepdrv" ],
    "time" : "2023-07-24T20:47:17.542Z"
  }, {
    "file" : "m",
    "line" : 451,
    "level" : "notice",
    "message" : "Lilamapu vacewo gabibobi miledeqony gejelafag zuvy nixocalig kyfap go rukoqef.",
    "source" : "Puppet",
    "tags" : [ "qsxfwaeof", "vzzcnhiqq", "evjmgskq", "yksijgtnzd", "notice", "itzhqf", "at", "wzx" ],
    "time" : "2023-07-24T20:47:17.542Z"
  }, {
    "file" : "GcOZUORK",
    "line" : 546,
    "level" : "notice",
    "message" : "Disusy byrov xuhetyr wuheqac hi wubyr kawo dehafuxe komif holewexiwu.",
    "source" : "Puppet",
    "tags" : [ "xywausbp", "znycfuvcgq", "npijfoxn", "obccywlzdq", "q", "kjnegclumt", "r", "notice", "qphsqgpt", "wlndyxiuf" ],
    "time" : "2023-07-24T20:47:17.542Z"
  }, {
    "file" : "tEF",
    "line" : 669,
    "level" : "notice",
    "message" : "Ha c dilu zotoku m tekojaxe xi toqudupote gusyni wubexefogif.",
    "source" : "Puppet",
    "tags" : [ "jip", "notice" ],
    "time" : "2023-07-24T20:47:17.542Z"
  }, {
    "file" : "BokImsLh",
    "line" : 310,
    "level" : "notice",
    "message" : "Jykihani jul r n bipe ru vydeg danew nyhecyg cupate.",
    "source" : "Puppet",
    "tags" : [ "rgjcvxwtl", "notice", "hbmcedmw" ],
    "time" : "2023-07-24T20:47:17.542Z"
  }, {
    "file" : "YBpvT",
    "line" : 217,
    "level" : "notice",
    "message" : "Buledap sedaxyqax hymyf mofutucajab suputulo bumehyl jegiwy kon lymil sakyquk.",
    "source" : "Puppet",
    "tags" : [ "en", "fhvcggvo", "qbrlq", "notice", "h", "vxrlgx", "rsopbvp" ],
    "time" : "2023-07-24T20:47:17.542Z"
  }, {
    "file" : "OlM",
    "line" : 203,
    "level" : "notice",
    "message" : "Vuwaliv qejuwu bopo jyjyge garulosyhu fibivydu by qivijinof kipoger ni.",
    "source" : "Puppet",
    "tags" : [ "ku", "cyubnhh", "jeqm", "notice", "ws" ],
    "time" : "2023-07-24T20:47:17.542Z"
  }, {
    "file" : "h",
    "line" : 380,
    "level" : "info",
    "message" : "Purob z l dywo pihomun g rukikujy kymecop biqyliwagiho narutavefeve.",
    "source" : "Puppet",
    "tags" : [ "igkb", "p", "info", "fbkttycwud", "fhjnsgqqsx" ],
    "time" : "2023-07-24T20:47:17.542Z"
  }, {
    "file" : null,
    "line" : null,
    "level" : "notice",
    "message" : "Applied catalog in 73.40 seconds",
    "source" : "Puppet",
    "tags" : [ "notice" ],
    "time" : "2023-07-24T20:47:15.979Z"
  } ],
  "report_format" : 12,
  "start_time" : "2023-07-19T02:19:16.671Z",
  "producer_timestamp" : "2023-07-19T02:19:59.586Z",
  "cached_catalog_status" : "not_used",
  "end_time" : "2023-07-19T02:19:58.586Z",
  "status" : "changed",
  "configuration_version" : "1690231635",
  "environment" : "production",
  "code_id" : "6311281d1ec11a68a6b0a7cb83c56236ff89e2ed",
  "resources" : [ {
    "corrective_change" : false,
    "events" : [ {
      "new_value" : "djsHRMnnOxqYpeUFwKSOAbbMXUufIVRQDQBsVtTsoBddVvhTTEbycHGVxb",
      "corrective_change" : false,
      "property" : "fezytu",
      "name" : "mehip_bafyl",
      "old_value" : "HKTyvFgHuJUkeXapnQuZUJpngYLORCRUKksSYKxFzkkLpHNoFFhRWeJalk",
      "status" : "success",
      "timestamp" : "2023-07-19T02:19:51.701Z",
      "message" : "reoJTKmFzBlQMVXRPNKJpsJOMnpjHYwxfGVdADvRBNyYwpWnEHSREZBGBM"
    } ],
    "file" : "MUG",
    "skipped" : false,
    "line" : 384,
    "resource_type" : "Class",
    "resource_title" : "class-vobixujaqyxufuzoximybyzobetusuvep-20",
    "timestamp" : "2023-07-19T02:19:51.671Z",
    "containment_path" : [ "Stage[main]", "Class[class-vobixujaqyxufuzoximybyzobetusuvep-20]" ]
  }, {
    "corrective_change" : false,
    "events" : [ {
      "new_value" : "tLnWLEloNrYwHmCspckAfjKKicbBhKKmpsrOMSMxXkVlrCKodRfKbTmbMlKkyYZDgEAFAivlGqtvPkaHzlBpOGEKWMGyarbknzSvtWXuXRVSdOxPgxOwswxPhhwvxdPcQ",
      "corrective_change" : false,
      "property" : "sexumy",
      "name" : "nod_qefusese",
      "old_value" : "MqxyVLOPNiqtlffSWOuVJMWrYxLqwartSUegTneMHJCHCDmoQzOXtbBbhXVkzVEajLxwlTxGxVtoLDNIgGqzufttEqLMxMSdunjitdqwZguVOGrvfMjUulEenfXSkHtWl",
      "status" : "success",
      "timestamp" : "2023-07-19T02:19:51.746Z",
      "message" : "WOwnEGiulSEWmpMQxZUMAreBejAhwckddfhAEObJxDiczjYEXtxQRFjYNHUKUMEaDUWoGdhrkOWbxNmfycAniSoyrioBnBIVSYzYwPodkPPVlrXCXizTFhnMuvrEhjTHN"
    } ],
    "file" : "YVSgtDP",
    "skipped" : false,
    "line" : 774,
    "resource_type" : "Class",
    "resource_title" : "class-motivufavuhixaqywyfezyjozyquryxeh-36",
    "timestamp" : "2023-07-19T02:19:51.734Z",
    "containment_path" : [ "Stage[main]", "Class[class-motivufavuhixaqywyfezyjozyquryxeh-36]" ]
  }, {
    "corrective_change" : false,
    "events" : [ {
      "new_value" : "DapNoffukAPqyD",
      "corrective_change" : false,
      "property" : "nyhery",
      "name" : "bedyx_zovap",
      "old_value" : "vvbigOQkHvavne",
      "status" : "success",
      "timestamp" : "2023-07-19T02:19:51.806Z",
      "message" : "yhInnAiLrzxkcI"
    } ],
    "file" : "KniVkyoQM",
    "skipped" : false,
    "line" : 625,
    "resource_type" : "Class",
    "resource_title" : "class-wynikikivydadasykecuqyteqadoleqeq-54",
    "timestamp" : "2023-07-19T02:19:51.785Z",
    "containment_path" : [ "Stage[main]", "Class[class-wynikikivydadasykecuqyteqadoleqeq-54]" ]
  }, {
    "corrective_change" : false,
    "events" : [ {
      "new_value" : "zAyHuOCPOXlHfaOZjivJQjCzTSRFvjLYEiQFSXoLSlvZaFOutfqxOuqodLlpbjVkRPPdmKqAOgNSNSrPiUEIyjZRhiRFaGFeenwOLblqHEoTBaXalAoSbSYtMBGsoVCsqJuIKQpndEolKpf",
      "corrective_change" : false,
      "property" : "fycevy",
      "name" : "hozyhy",
      "old_value" : "ySzcwMNJSBfsjkcNrqoFUdjaWIiPcAUPZlZQRYliUmEQcjvlrptEDSUdUyUqBDkdvsDXtXVuNkZKqNHNFdjmYahUIeVWirvJpPvxLdfdQXcEsgLlCPFNwwgPwDfmZrDBcOUavacMTLNGehM",
      "status" : "success",
      "timestamp" : "2023-07-19T02:19:51.867Z",
      "message" : "TLJKzReVbQTdGNbNimOeFNdBinSTDhYDPQqZQZUZLBYYsYkjMbvmgaEoRGSAtRXRQqtmeUvHkKcNMuGTbZuIvSsXJpbdCWOzenLZMXwgWDIwtCXJIGcjNtbuLgHNIlJXhLqURJJAqLyMiKH"
    } ],
    "file" : "LA",
    "skipped" : false,
    "line" : 838,
    "resource_type" : "Class",
    "resource_title" : "class-tucihikitigomidisolizyxyperywureq-81",
    "timestamp" : "2023-07-19T02:19:51.840Z",
    "containment_path" : [ "Stage[main]", "Class[class-tucihikitigomidisolizyxyperywureq-81]" ]
  }, {
    "corrective_change" : false,
    "events" : [ {
      "new_value" : "zZVihIyXEXhoFrKbrPPRtZFqJLA",
      "corrective_change" : false,
      "property" : "hukuti",
      "name" : "xagy_syk",
      "old_value" : "ZNhLZcXAbTbbYjyevzWCSMjrqjO",
      "status" : "success",
      "timestamp" : "2023-07-19T02:19:51.885Z",
      "message" : "WBmFbyzbYbRdxCZMdRVXEYNJpoD"
    } ],
    "file" : "YF",
    "skipped" : false,
    "line" : 955,
    "resource_type" : "Package",
    "resource_title" : "resource-rumupodysulakarovybusuqezerywy-13",
    "timestamp" : "2023-07-19T02:19:51.883Z",
    "containment_path" : [ "Stage[main]", "Class[class-muzahitucokylopaqogususozuwabuduv-34]", "Package[resource-rumupodysulakarovybusuqezerywy-13]" ]
  }, {
    "corrective_change" : false,
    "events" : [ {
      "new_value" : "rIi",
      "corrective_change" : false,
      "property" : "vatuwu",
      "name" : "lake_qidekur",
      "old_value" : "QlK",
      "status" : "success",
      "timestamp" : "2023-07-19T02:19:51.939Z",
      "message" : "Bagon walageheh byjatal l gyd."
    } ],
    "file" : "oGMgfWfR",
    "skipped" : false,
    "line" : 470,
    "resource_type" : "User",
    "resource_title" : "resource-vusywerimogidesygudacihazumowo-74",
    "timestamp" : "2023-07-19T02:19:51.897Z",
    "containment_path" : [ "Stage[main]", "Class[class-gokopajuvawejunahyreninijuvovuluk-76]", "User[resource-vusywerimogidesygudacihazumowo-74]" ]
  }, {
    "corrective_change" : false,
    "events" : [ {
      "new_value" : "aZjRextFFaxv",
      "corrective_change" : false,
      "property" : "pyluhy",
      "name" : "gaqi_wo",
      "old_value" : "KyMRVRvSjlnT",
      "status" : "success",
      "timestamp" : "2023-07-19T02:19:52.016Z",
      "message" : "LiSTAiKxMyxF"
    } ],
    "file" : "GcOZUORK",
    "skipped" : false,
    "line" : 546,
    "resource_type" : "Exec",
    "resource_title" : "resource-wokukobemavyhilyqonidezoporazi-85",
    "timestamp" : "2023-07-19T02:19:51.991Z",
    "containment_path" : [ "Stage[main]", "Class[class-sonuwagydyhejokopyvedyvoracywytig-98]", "Exec[resource-wokukobemavyhilyqonidezoporazi-85]" ]
  }, {
    "corrective_change" : false,
    "events" : [ {
      "new_value" : "NqkLfSGTqDR",
      "corrective_change" : false,
      "property" : "kegyfe",
      "name" : "wimuku",
      "old_value" : "FPPkytbpIhM",
      "status" : "success",
      "timestamp" : "2023-07-19T02:19:52.064Z",
      "message" : "xQExVMSyiXl"
    } ],
    "file" : "LbxcCDIik",
    "skipped" : false,
    "line" : 617,
    "resource_type" : "Service",
    "resource_title" : "resource-lywytivuvudufojaqomupyliguzud-104",
    "timestamp" : "2023-07-19T02:19:52.052Z",
    "containment_path" : [ "Stage[main]", "Class[class-davuhosoxyrikitivesenohijekefuwat-41]", "Service[resource-lywytivuvudufojaqomupyliguzud-104]" ]
  }, {
    "corrective_change" : false,
    "events" : [ {
      "new_value" : "PijRWuoxUKeepVoEcckbeqadProRQHjFBKxPDjTAaIKPKCFdvFDLxNPRMEaPYnGgfHzReJULMPwJypgBLlKsNZyOYEOLFiOXnimoXSFbqjtCdapFN",
      "corrective_change" : false,
      "property" : "huvaji",
      "name" : "suxut_ficoki",
      "old_value" : "CvuQoIWSxwfSpcAdqfWmShXbChXlEXyHnWigjARqIuUplCeLzewwigkJLDxaIrkiyXUSPaTxhrmAaLCPPAuMqSbLKjFXDwxoHzKbymLcQoJcMgmVb",
      "status" : "success",
      "timestamp" : "2023-07-19T02:19:52.188Z",
      "message" : "RvJJDvtdFyvEhSmyhuEvWsyOKnntnWlSafSbXxbVhjIpCtZsrtcEnaFMXpbuVPdslySmZXrkbUpcOjhNFWlrEMeBVOOsTkIiDfbXDmawpfOIgKpsK"
    } ],
    "file" : "m",
    "skipped" : false,
    "line" : 451,
    "resource_type" : "Service",
    "resource_title" : "resource-cytekaqosigahunymahulodopysuj-131",
    "timestamp" : "2023-07-19T02:19:52.156Z",
    "containment_path" : [ "Stage[main]", "Class[class-zaqekahudybepesizakanihoqusuqozih-94]", "Service[resource-cytekaqosigahunymahulodopysuj-131]" ]
  }, {
    "corrective_change" : false,
    "events" : [ {
      "new_value" : "HrqeflnfbBlActnzptsUdBXcmzpuYzLfhlfZxNphXzwkRCiwJDcTMfjIYCsgENeWEihTWgnyRAZAuszlFurFGGJXLDwuZxSWwpGvMF",
      "corrective_change" : false,
      "property" : "cusede",
      "name" : "zyri_vykyjutugyd",
      "old_value" : "LKEmNNqjvuzRkDaiiYfkMnnrNTGdlDFkuXlXtLlkWiuMkGZtoTiFKKUJwYhsYOfwHsrqoDMtCnsuHIHapwvFGQDjZKULcAGeOeHapH",
      "status" : "success",
      "timestamp" : "2023-07-19T02:19:52.317Z",
      "message" : "QtcUBnBctOMTEGxxqMUQDolkYAOiVXGBqshgFrzWtuxaZywrtZidfEmwLGjMfQtyjWnofvILCZNhnndtkzCFLokPQCmEigcPzhgOQK"
    } ],
    "file" : "YAwrm",
    "skipped" : false,
    "line" : 280,
    "resource_type" : "Lynirypu::Cikuzapewizajegut",
    "resource_title" : "resource-zoxyrokymalorycupiziwoxesiqas-142",
    "timestamp" : "2023-07-19T02:19:52.275Z",
    "containment_path" : [ "Stage[main]", "Class[class-tuxikubiripihulokacunogafaxeqevic-25]", "Lynirypu::Cikuzapewizajegut[resource-zoxyrokymalorycupiziwoxesiqas-142]" ]
  }, {
    "corrective_change" : false,
    "events" : [ {
      "new_value" : "IeCV",
      "corrective_change" : false,
      "property" : "quneqa",
      "name" : "posylyzec",
      "old_value" : "fgZF",
      "status" : "success",
      "timestamp" : "2023-07-19T02:19:52.443Z",
      "message" : "Dedesymehiwa xobepykuf ceda guhyjas rat."
    } ],
    "file" : "g",
    "skipped" : false,
    "line" : 851,
    "resource_type" : "Sefajisesupohus",
    "resource_title" : "resource-wokizysenecevybuzisetenucigyz-151",
    "timestamp" : "2023-07-19T02:19:52.394Z",
    "containment_path" : [ "Stage[main]", "Class[class-xurukobyrifybaxafisofuhivydosenux-89]", "Sefajisesupohus[resource-wokizysenecevybuzisetenucigyz-151]" ]
  }, {
    "corrective_change" : false,
    "events" : [ {
      "new_value" : "ngXKSTEmWsidRxLwsuUFidbBfWYkgAwyosRUwLUKYAoApmkFthHtTQcBKuSviiTcLKmyArRBAHjDvyDcRNhORQatPyKIjxfkuMPgTYVQhYZrsdplwkNaZNkZoWquZIqhphwHSoC",
      "corrective_change" : false,
      "property" : "maxyme",
      "name" : "vofyhizos",
      "old_value" : "ouQJXhNNBxJnlJfKheXfwqPlTlRBoDytttYrWTUyeGuisJXNNeCCBJDGDBitynWrqTIKWuuCCMVdRgLtKhOcAbsPNYmEiIhnypQZaiMpIiOZYVajamtgsjgZmYuWRwCsEbfSovJ",
      "status" : "success",
      "timestamp" : "2023-07-19T02:19:52.549Z",
      "message" : "CuNlJdSaqjKnTZoXDWFOYkopiXObTjDavxfPwiozWGHzpdsZLLQeGpEWCsUfxXutSQNyMnXJAHYSjCZMOtCVAlozwAPYhrKexCuzPJkyeDAuVhRBdOkzGmZiYntmNUbbBxhYGJb"
    } ],
    "file" : "HvzOM",
    "skipped" : false,
    "line" : 321,
    "resource_type" : "Fobixugeqa::Bufafenyzehufyryt",
    "resource_title" : "resource-helimigenogesacejerogizobibeg-152",
    "timestamp" : "2023-07-19T02:19:52.505Z",
    "containment_path" : [ "Stage[main]", "Class[class-qesevoqytabetunepeqexedeqewixacaje-9]", "Fobixugeqa::Bufafenyzehufyryt[resource-helimigenogesacejerogizobibeg-152]" ]
  }, {
    "corrective_change" : false,
    "events" : [ {
      "new_value" : "QOioQBflOwvUtnEDXrtdVICopSIcXTOmYGbEtZKpnyAoCVhxMjPZtDoQPsxdB",
      "corrective_change" : false,
      "property" : "satafy",
      "name" : "fyvoly",
      "old_value" : "fVspDqnVwnDVipMrKSnNeBjfFfmhdjQxayRllsMGCOClkHHByobemjUyaWcNE",
      "status" : "success",
      "timestamp" : "2023-07-19T02:19:52.688Z",
      "message" : "UOPWGcNaXRKQXiKdFSpgYeBAqKTcdJvSnYcKsKxhGHNlPXyWQvQCqZFjcpAzL"
    } ],
    "file" : "h",
    "skipped" : false,
    "line" : 380,
    "resource_type" : "Package",
    "resource_title" : "resource-juwavyzoxyvymeditinopydupygub-153",
    "timestamp" : "2023-07-19T02:19:52.639Z",
    "containment_path" : [ "Stage[main]", "Class[class-byxelehazawyxygijicatavohetozagyb-29]", "Package[resource-juwavyzoxyvymeditinopydupygub-153]" ]
  }, {
    "corrective_change" : false,
    "events" : [ {
      "new_value" : "gHSuDK",
      "corrective_change" : false,
      "property" : "rocivi",
      "name" : "xumikefada",
      "old_value" : "gfqfFA",
      "status" : "success",
      "timestamp" : "2023-07-19T02:19:52.784Z",
      "message" : "L qisi p zupurehon nitewyle."
    } ],
    "file" : "ZiFXf",
    "skipped" : false,
    "line" : 980,
    "resource_type" : "Package",
    "resource_title" : "resource-wuxajyrorusidevinekovibuxozyz-177",
    "timestamp" : "2023-07-19T02:19:52.772Z",
    "containment_path" : [ "Stage[main]", "Class[class-tudulyhoqanusedilupojaniwehokexet-90]", "Package[resource-wuxajyrorusidevinekovibuxozyz-177]" ]
  }, {
    "corrective_change" : false,
    "events" : [ {
      "new_value" : "EgoFyTyFSVUgxOnznpMTnKgvgtPpILCZUgCMxQdKCFuHENuBQCrPbYWyOBNdizUhpQo",
      "corrective_change" : false,
      "property" : "tamasy",
      "name" : "mekokaj",
      "old_value" : "chUHvbqajAKSoIcoAUrdvqKTbXqglPvuOMjBuSCijDmYZQoUnEbhCBJlKlAtDFBzbGM",
      "status" : "success",
      "timestamp" : "2023-07-19T02:19:52.904Z",
      "message" : "lgiJDpWyacRBbIbpNBTHoKoLHbXNJLFJdpZMnKbtjWneUTKsKBPVEunQoJyfFTtsguq"
    } ],
    "file" : "EaxiBhED",
    "skipped" : false,
    "line" : 818,
    "resource_type" : "User",
    "resource_title" : "resource-vepamekiwynynenirupoviwaqawag-190",
    "timestamp" : "2023-07-19T02:19:52.876Z",
    "containment_path" : [ "Stage[main]", "Class[class-tonenezuvicafiledotabufehipolowoz-55]", "User[resource-vepamekiwynynenirupoviwaqawag-190]" ]
  }, {
    "corrective_change" : false,
    "events" : [ {
      "new_value" : "HuboZUuUSxHAJbSvwMZYfeSPLIy",
      "corrective_change" : false,
      "property" : "tiqone",
      "name" : "vityva",
      "old_value" : "cTuURgZcJTNyGhVONhcKdqGqUSC",
      "status" : "success",
      "timestamp" : "2023-07-19T02:19:52.969Z",
      "message" : "EmGflTrYdeLGmjXsNpupovbQJXC"
    } ],
    "file" : "YBpvT",
    "skipped" : false,
    "line" : 217,
    "resource_type" : "Package",
    "resource_title" : "resource-fejilafucofewaborenewegirarag-199",
    "timestamp" : "2023-07-19T02:19:52.963Z",
    "containment_path" : [ "Stage[main]", "Class[class-wokeqezajabafiwavojuwudukuhegoxyh-30]", "Package[resource-fejilafucofewaborenewegirarag-199]" ]
  }, {
    "corrective_change" : false,
    "events" : [ {
      "new_value" : "repHrydHUthScokgWbTCGkwYLkMmQxlZSVZdhnVRWVLhzswuSKxiiwbrljFxdDThVUucRDovLeIMSFVAtSuOXGsBPzNEPsecmotBzZ",
      "corrective_change" : false,
      "property" : "zosomo",
      "name" : "qunaxi",
      "old_value" : "gYLVeQUqollnGhmEGTkeWqCSUyESgAIciAaMZpwpNdQoygdzUcaRSpGtGdPWQNBEwEubvDqywLLMeohqXbUpUEvcIksvptufkKITrq",
      "status" : "success",
      "timestamp" : "2023-07-19T02:19:53.044Z",
      "message" : "anTLhMqEYnBsMaBuglnrzijRfiIQpMsldgqmZvPdfHLuFUQJaRkmIKJEBaIiobNHTvMOnHfCvcCOHZcDLXKuOfpEjWXhoXFPCVJoSZ"
    } ],
    "file" : "uzmD",
    "skipped" : false,
    "line" : 429,
    "resource_type" : "File",
    "resource_title" : "resource-mizoxydyrypeqyhuqycacalagaquf-210",
    "timestamp" : "2023-07-19T02:19:53.026Z",
    "containment_path" : [ "Stage[main]", "Class[class-tuxikubiripihulokacunogafaxeqevic-25]", "File[resource-mizoxydyrypeqyhuqycacalagaquf-210]" ]
  }, {
    "corrective_change" : false,
    "events" : [ {
      "new_value" : "HPtGyeagwvUnLSEcganESjmdceXsJFGMVoAVAfisDuYSsjzNzvmABwcNIjuSljphqPpXHgTyflMPYQYvfRnJCoEP",
      "corrective_change" : false,
      "property" : "gyxaki",
      "name" : "rab_xobuqi",
      "old_value" : "ehaiJmkcPbrWoVIOjjfEspHQMyVybupVhffMJtdXkWsZPTNpYNijtnwAHNXptfrYmKHHYfaFEyIhpttpVIjThizZ",
      "status" : "success",
      "timestamp" : "2023-07-19T02:19:53.100Z",
      "message" : "jMtjxTIDICdXBHmUthhZkkwlvskkrruBjjTqttuajnGMwpfUwIRSnlYcmSeUwYufkTxAkHUSBPnnDQophGVhRRQO"
    } ],
    "file" : "EtjQQdk",
    "skipped" : false,
    "line" : 174,
    "resource_type" : "Package",
    "resource_title" : "resource-gohaxokurumutuxevumebuvelaxaf-217",
    "timestamp" : "2023-07-19T02:19:53.081Z",
    "containment_path" : [ "Stage[main]", "Class[class-cegylasejajyxedevokazymefoziwenev-72]", "Package[resource-gohaxokurumutuxevumebuvelaxaf-217]" ]
  }, {
    "corrective_change" : false,
    "events" : [ {
      "new_value" : "syrlAWbMM",
      "corrective_change" : false,
      "property" : "givaxu",
      "name" : "pokime",
      "old_value" : "XchAHoLsA",
      "status" : "success",
      "timestamp" : "2023-07-19T02:19:53.132Z",
      "message" : "Nera tekeponifez ma fajubica kopysufikero."
    } ],
    "file" : "OkUwlz",
    "skipped" : false,
    "line" : 5,
    "resource_type" : "Bavosohelixunu",
    "resource_title" : "resource-niditypugumikavavolyhojenubev-251",
    "timestamp" : "2023-07-19T02:19:53.132Z",
    "containment_path" : [ "Stage[main]", "Class[class-ladekyquhenawowyzytiqynanutuqylej-82]", "Bavosohelixunu[resource-niditypugumikavavolyhojenubev-251]" ]
  }, {
    "corrective_change" : false,
    "events" : [ {
      "new_value" : "MVFUeqJDlNDElkFYrrZPXW",
      "corrective_change" : false,
      "property" : "komoco",
      "name" : "daqi_nyfogagy",
      "old_value" : "DomAQYPKeDaoLZNHgGQqsZ",
      "status" : "success",
      "timestamp" : "2023-07-19T02:19:53.211Z",
      "message" : "aMlEdcmgFOVOqVdorshfZx"
    } ],
    "file" : "hq",
    "skipped" : false,
    "line" : 294,
    "resource_type" : "Exec",
    "resource_title" : "resource-xutyxolubavanurenujumogocyfym-254",
    "timestamp" : "2023-07-19T02:19:53.206Z",
    "containment_path" : [ "Stage[main]", "Class[class-sewumajihudisejolacejeqegezuqenuc-62]", "Exec[resource-xutyxolubavanurenujumogocyfym-254]" ]
  }, {
    "corrective_change" : false,
    "events" : [ {
      "new_value" : "NkEsXQpgGGZJEZBUjPbZEiTnqQ",
      "corrective_change" : false,
      "property" : "soluqa",
      "name" : "zyno_namiq",
      "old_value" : "dPpsOqukGYOpHTJSiXTqiteVdf",
      "status" : "success",
      "timestamp" : "2023-07-19T02:19:53.247Z",
      "message" : "hFJtrNhJaxzcGWPYauhcfYrHQJ"
    } ],
    "file" : "pbgrdP",
    "skipped" : false,
    "line" : 802,
    "resource_type" : "Cyvulenafykaz::Sevafimuhod",
    "resource_title" : "resource-byxavelejanizakulawykizytypaf-272",
    "timestamp" : "2023-07-19T02:19:53.214Z",
    "containment_path" : [ "Stage[main]", "Class[class-cegylasejajyxedevokazymefoziwenev-72]", "Cyvulenafykaz::Sevafimuhod[resource-byxavelejanizakulawykizytypaf-272]" ]
  }, {
    "corrective_change" : false,
    "events" : [ {
      "new_value" : "tlFzNHjmDR",
      "corrective_change" : false,
      "property" : "horuzi",
      "name" : "fih_tyky",
      "old_value" : "kzbEWvEnmw",
      "status" : "success",
      "timestamp" : "2023-07-19T02:19:53.274Z",
      "message" : "TCBKELMize"
    } ],
    "file" : "BokImsLh",
    "skipped" : false,
    "line" : 310,
    "resource_type" : "Package",
    "resource_title" : "resource-picizybeninafibufuhedaxaqytag-278",
    "timestamp" : "2023-07-19T02:19:53.259Z",
    "containment_path" : [ "Stage[main]", "Class[class-rymuqobapiwakeredycajatiwapygihag-16]", "Package[resource-picizybeninafibufuhedaxaqytag-278]" ]
  }, {
    "corrective_change" : false,
    "events" : [ {
      "new_value" : "lxZjvitrtayavyLFZe",
      "corrective_change" : false,
      "property" : "sufogu",
      "name" : "jefajy",
      "old_value" : "vJvSCrWEsnRQWOYPgD",
      "status" : "success",
      "timestamp" : "2023-07-19T02:19:53.322Z",
      "message" : "rJopPoODOTZyfkbqFv"
    } ],
    "file" : "RQ",
    "skipped" : false,
    "line" : 865,
    "resource_type" : "File",
    "resource_title" : "resource-xybojisalimynytyhococofyjokyb-314",
    "timestamp" : "2023-07-19T02:19:53.316Z",
    "containment_path" : [ "Stage[main]", "Class[class-lypimubytusozumuhehikehewyjunotul-27]", "File[resource-xybojisalimynytyhococofyjokyb-314]" ]
  }, {
    "corrective_change" : false,
    "events" : [ {
      "new_value" : "rwaLrDcBjUuZQHwXZHVPc",
      "corrective_change" : false,
      "property" : "suhisi",
      "name" : "meqiw_cydu",
      "old_value" : "cofRQdGxpmELSqQBHxrDx",
      "status" : "success",
      "timestamp" : "2023-07-19T02:19:53.405Z",
      "message" : "bWxhwNOWpcwsxoGeWkCyC"
    } ],
    "file" : "axy",
    "skipped" : false,
    "line" : 432,
    "resource_type" : "Service",
    "resource_title" : "resource-fituqijacedavukugydoxigusevit-317",
    "timestamp" : "2023-07-19T02:19:53.397Z",
    "containment_path" : [ "Stage[main]", "Class[class-sonyxijixumazutydizibururiqokopux-42]", "Service[resource-fituqijacedavukugydoxigusevit-317]" ]
  }, {
    "corrective_change" : false,
    "events" : [ {
      "new_value" : "eneayoZemSjsTqepkUlMuWpByEwDvitpuFxWYjHjMrjWGHrpIKowujgIuGKaPkUPxIaWwsgsZQKVOsonqUUdQpahtUhVbhYEQqhotl",
      "corrective_change" : false,
      "property" : "pyzifu",
      "name" : "jymu_rysy",
      "old_value" : "KNIAhNiUUcUMmzkrZFUuVNtcfQHyPYrcVjYlyjDULeAdXvkvGMajkDzldCWTXIqxpOOdByYvnBEEdWSCHSMVJPTwavygVmRKcNpSRD",
      "status" : "success",
      "timestamp" : "2023-07-19T02:19:53.459Z",
      "message" : "xfZDeKklBPemlKBdyvlWfvJltbuxqrjBlYtOIMaFbgvJCBOAxXoctGGWPVtyJkCeFTqqwKfhFLsBhzbXVyBuiKcYofHweEqnZeCGyl"
    } ],
    "file" : "jFlp",
    "skipped" : false,
    "line" : 899,
    "resource_type" : "Service",
    "resource_title" : "resource-gizireligubucuhyduxizitewavyv-319",
    "timestamp" : "2023-07-19T02:19:53.410Z",
    "containment_path" : [ "Stage[main]", "Class[class-wokeqezajabafiwavojuwudukuhegoxyh-30]", "Service[resource-gizireligubucuhyduxizitewavyv-319]" ]
  }, {
    "corrective_change" : false,
    "events" : [ {
      "new_value" : "UntSZauavxbJDByY",
      "corrective_change" : false,
      "property" : "lyhyso",
      "name" : "duh_koqy",
      "old_value" : "nKsOqDbmeyDumVhD",
      "status" : "success",
      "timestamp" : "2023-07-19T02:19:53.527Z",
      "message" : "GtZkyzLNxHeqHqMp"
    } ],
    "file" : "Et",
    "skipped" : false,
    "line" : 817,
    "resource_type" : "Exec",
    "resource_title" : "resource-faxasofapatibypycusanybysutev-322",
    "timestamp" : "2023-07-19T02:19:53.522Z",
    "containment_path" : [ "Stage[main]", "Class[class-wyhequguwehajusemudesiniqyjylogyj-64]", "Exec[resource-faxasofapatibypycusanybysutev-322]" ]
  }, {
    "corrective_change" : false,
    "events" : [ {
      "new_value" : "nWDoKrTNctjnQEyeXkFwBfNZEqtFexqYiKHciOquzVarzhWHDPkxynXCXUFfcSukYfnJLAUJYzNRImWXPB",
      "corrective_change" : false,
      "property" : "fisazo",
      "name" : "qirem_kogymix",
      "old_value" : "UOMugLmJrVwyxyZoPngIexhHcTXlnJQfRekqDjnKyvJjEGEQrLbThGJGrcOkveOgotDhuwKqRozKSArBmp",
      "status" : "success",
      "timestamp" : "2023-07-19T02:19:53.569Z",
      "message" : "oJubIVjaqqbEObjGOSmNYCDBXJgrAZsNwUEvaFnJweOKfLFrwEOTTSaticUVGsEQroNrSLBJgNIOKYnmKz"
    } ],
    "file" : "OlM",
    "skipped" : false,
    "line" : 203,
    "resource_type" : "Exec",
    "resource_title" : "resource-ninehewaragajotynaquzaqokysis-373",
    "timestamp" : "2023-07-19T02:19:53.559Z",
    "containment_path" : [ "Stage[main]", "Class[class-dugakifujuxomejudagumiqizosogygeh-15]", "Exec[resource-ninehewaragajotynaquzaqokysis-373]" ]
  }, {
    "corrective_change" : false,
    "events" : [ {
      "new_value" : "hwcZUobktQYUDziOq",
      "corrective_change" : false,
      "property" : "gufete",
      "name" : "gepohe",
      "old_value" : "FinZyRqsMclWULPkM",
      "status" : "success",
      "timestamp" : "2023-07-19T02:19:53.647Z",
      "message" : "DYIsVsehZTYYvdurR"
    } ],
    "file" : "Zjt",
    "skipped" : false,
    "line" : 138,
    "resource_type" : "File",
    "resource_title" : "resource-kytywupypofurafuliwirojonuzej-380",
    "timestamp" : "2023-07-19T02:19:53.620Z",
    "containment_path" : [ "Stage[main]", "Class[class-dugakifujuxomejudagumiqizosogygeh-15]", "File[resource-kytywupypofurafuliwirojonuzej-380]" ]
  }, {
    "corrective_change" : false,
    "events" : [ {
      "new_value" : "oJHYfErrdaWNqb",
      "corrective_change" : false,
      "property" : "dyzubo",
      "name" : "sihobevitiv",
      "old_value" : "pacnoBLqwGDkAi",
      "status" : "success",
      "timestamp" : "2023-07-19T02:19:53.752Z",
      "message" : "lkLgtMtukzUrpL"
    } ],
    "file" : "MxbzDrMX",
    "skipped" : false,
    "line" : 499,
    "resource_type" : "Vixyzaw::Xujorokaxuxe::Lezyn",
    "resource_title" : "resource-didurihocezegiwolovyqaxocokyv-442",
    "timestamp" : "2023-07-19T02:19:53.741Z",
    "containment_path" : [ "Stage[main]", "Class[class-lypimubytusozumuhehikehewyjunotul-27]", "Vixyzaw::Xujorokaxuxe::Lezyn[resource-didurihocezegiwolovyqaxocokyv-442]" ]
  }, {
    "corrective_change" : false,
    "events" : [ {
      "new_value" : "QggUJPSZnfLkHtekNtZinNvJ",
      "corrective_change" : false,
      "property" : "qivacy",
      "name" : "qewuje",
      "old_value" : "kPWqZFLSJANSfqCyqovudVhC",
      "status" : "success",
      "timestamp" : "2023-07-19T02:19:53.782Z",
      "message" : "DNMSXZEjRlycvqtUwXxrBtws"
    } ],
    "file" : "CKFdoViHa",
    "skipped" : false,
    "line" : 764,
    "resource_type" : "Zohyzoxof::Mabuqyxypyk::Pypyqomy::Xovug",
    "resource_title" : "resource-qekalogorijuzituwevogamomekun-476",
    "timestamp" : "2023-07-19T02:19:53.777Z",
    "containment_path" : [ "Stage[main]", "Class[class-nowycodykekyhyxujalizuvaxuxibyxiv-46]", "Zohyzoxof::Mabuqyxypyk::Pypyqomy::Xovug[resource-qekalogorijuzituwevogamomekun-476]" ]
  }, {
    "corrective_change" : false,
    "events" : [ {
      "new_value" : "FnFHzsqUhlDJmwXLH",
      "corrective_change" : false,
      "property" : "gobytu",
      "name" : "xuh_zoreqyk",
      "old_value" : "UrVkLMAqytyLaUQdm",
      "status" : "success",
      "timestamp" : "2023-07-19T02:19:53.896Z",
      "message" : "EGsvKDwgMrMCfHUJy"
    } ],
    "file" : "L",
    "skipped" : false,
    "line" : 327,
    "resource_type" : "Service",
    "resource_title" : "resource-pulelymicanarogijipuzemuxizom-511",
    "timestamp" : "2023-07-19T02:19:53.875Z",
    "containment_path" : [ "Stage[main]", "Class[class-hutamyjisufywusiwezawomyhesubimup-77]", "Service[resource-pulelymicanarogijipuzemuxizom-511]" ]
  }, {
    "corrective_change" : false,
    "events" : [ {
      "new_value" : "KGNbKdgyn",
      "corrective_change" : false,
      "property" : "heqybe",
      "name" : "lyqumady",
      "old_value" : "oTRnldWqn",
      "status" : "success",
      "timestamp" : "2023-07-19T02:19:53.972Z",
      "message" : "Zujyf basarake jatiby weqilox pabypyma."
    } ],
    "file" : "tEF",
    "skipped" : false,
    "line" : 669,
    "resource_type" : "User",
    "resource_title" : "resource-wyjohilukugebilimaruhudolalot-550",
    "timestamp" : "2023-07-19T02:19:53.941Z",
    "containment_path" : [ "Stage[main]", "Class[class-pexisitedyjecisabesejimycymozuwod-97]", "User[resource-wyjohilukugebilimaruhudolalot-550]" ]
  }, {
    "corrective_change" : false,
    "events" : [ {
      "new_value" : "AyPuUqVPsbyNAEPEBPdUvavTBazDgXQXTAKzNEfMAUNDjIgAZcFXIKJLfdqRvdQuWYsFfmDOByMhhTbgXMUZVncgkjOCpMeFYxwsVSLXEsiSifVDSfb",
      "corrective_change" : false,
      "property" : "zynifo",
      "name" : "rytihyg",
      "old_value" : "ObdaluJcEsRnrAxigXvRmCMGnELsllXSDBHUmkJzIPcMyJkKUydueRGhWpkBKecZlGReUlZuHvbofcVZqFodaaiLwVedSauiAujAgCYpcNkPxQApkqF",
      "status" : "success",
      "timestamp" : "2023-07-19T02:19:54.057Z",
      "message" : "TgILbVisoFzwOPPxKvTEuSKDDNuvDReVaLTudOkhangTQPTLhszBmwzkBmcGeXNLxvqyjOZhPumdXhYJaCrjpNTwEGmNUeduKinuPYrqFWWMAnZkCWk"
    } ],
    "file" : "KlQlEvr",
    "skipped" : false,
    "line" : 585,
    "resource_type" : "User",
    "resource_title" : "resource-nozanagybijifaguqyciridyzitof-572",
    "timestamp" : "2023-07-19T02:19:54.042Z",
    "containment_path" : [ "Stage[main]", "Class[class-hylobelagarypijemisecopebifecuves-23]", "User[resource-nozanagybijifaguqyciridyzitof-572]" ]
  }, {
    "corrective_change" : false,
    "events" : [ {
      "new_value" : "whsjAldFE",
      "corrective_change" : false,
      "property" : "bebaxa",
      "name" : "dyxyjota",
      "old_value" : "aaVJINFtD",
      "status" : "success",
      "timestamp" : "2023-07-19T02:19:54.133Z",
      "message" : "Kocaxo pic woji kahewypop qyqopanapi."
    } ],
    "file" : "MqSeZP",
    "skipped" : false,
    "line" : 860,
    "resource_type" : "Jalup",
    "resource_title" : "resource-pahysajexerygosilegenorytuhaq-587",
    "timestamp" : "2023-07-19T02:19:54.091Z",
    "containment_path" : [ "Stage[main]", "Class[class-qonufonejipuwyrohidegylovoryvanuf-11]", "Jalup[resource-pahysajexerygosilegenorytuhaq-587]" ]
  }, {
    "corrective_change" : false,
    "events" : [ {
      "new_value" : "sZUButQfSLbKxdFPQniTEQBEVmaRIdrugMhcoUghmhTNryrJiduNcsxcYDyTCciqhyWuljoOKNvYCTvrtCOivcdDyWbpy",
      "corrective_change" : false,
      "property" : "qamoto",
      "name" : "jofi_syfefyk",
      "old_value" : "dkpeMLJEqHanUQIgKRoltPCGHjsCYWyjRytWspjMbcYZhbXDFifLNkWmousYrJTWFdaZsoMmjDKWdGOkuIiHbvuHEJULn",
      "status" : "success",
      "timestamp" : "2023-07-19T02:19:54.164Z",
      "message" : "ooDQcJokJpqiheIGSmmTGPichWPnVJHUUpwORtxhrcKebhORUJQSkIPnlMvkPyNtABNbUpBMFbmVGKxkrnsHMtOoSgFqO"
    } ],
    "file" : "ylYYDboI",
    "skipped" : false,
    "line" : 865,
    "resource_type" : "Exec",
    "resource_title" : "resource-qadawydapyrihifoganaqocapohat-592",
    "timestamp" : "2023-07-19T02:19:54.136Z",
    "containment_path" : [ "Stage[main]", "Class[class-ladekyquhenawowyzytiqynanutuqylej-82]", "Exec[resource-qadawydapyrihifoganaqocapohat-592]" ]
  }, {
    "corrective_change" : false,
    "events" : [ {
      "new_value" : "SFGRuiwXbjGafgTihYNgczxJfzbevHpVaoEYVXUkTurvlTQnmPtafiSilASquRrWDXEoMPkDQACNNsasXIdrBrhyrhwAhtmtitapfEptDFposgqRcBiGtzDhNGLPJkwtbv",
      "corrective_change" : false,
      "property" : "bacale",
      "name" : "jodaq_simetyk",
      "old_value" : "BqlalFNUrcFxHCCedWYfCQnHXOtCrnUxAAsqlFDCIpNHlzZNAThEJQZqDFhUKCikaOvPwmffRhPAPvdycdKPeRnbFPjkVeeYiBTtxkQmvGlGJsncVDAtIEUWcyJbqAOEPx",
      "status" : "success",
      "timestamp" : "2023-07-19T02:19:54.229Z",
      "message" : "abAHwuaAjLUtHGSHpFBdILaTteLnbWeIwnRisJMZSHwUFCBUaqgMimIGgRjdBQoYpKPTvtgKoigmCAeQiLOdLzOKVFCwMxQQaBXOYHflxIOGQNyTHTgmEyakPQDtPwhNop"
    } ],
    "file" : "KfCsnaAbug",
    "skipped" : false,
    "line" : 280,
    "resource_type" : "Exec",
    "resource_title" : "resource-jenurafosygejehyhozalesypokeb-593",
    "timestamp" : "2023-07-19T02:19:54.228Z",
    "containment_path" : [ "Stage[main]", "Class[class-wyqenawijicehekakynahexozejivocoq-32]", "Exec[resource-jenurafosygejehyhozalesypokeb-593]" ]
  }, {
    "corrective_change" : false,
    "events" : [ {
      "new_value" : "ZaTWKGzHrMhIPVuiCZCLOMbhCmzrKgPYwVlnxuwYBuwyrjqWOshSEYNxCqXH",
      "corrective_change" : false,
      "property" : "dopofi",
      "name" : "xijefox",
      "old_value" : "gAxjweOvdCLBZbrKmcmDAJwJcLSrfEZlppSSeNBvOmBtoXgKFLoAGAtXYOgY",
      "status" : "success",
      "timestamp" : "2023-07-19T02:19:54.299Z",
      "message" : "dyXTZcgNjWouzmQbHoqpwwDdMrNRtBTkSoxmCufeuRYLYiYdfTWsngvLTbZE"
    } ],
    "file" : "uoPEpLXxIO",
    "skipped" : false,
    "line" : 606,
    "resource_type" : "Exec",
    "resource_title" : "resource-hebifedexodumexyhecorukuzafaj-607",
    "timestamp" : "2023-07-19T02:19:54.267Z",
    "containment_path" : [ "Stage[main]", "Class[class-wejyfodiboxegejisidydoguhupypigux-87]", "Exec[resource-hebifedexodumexyhecorukuzafaj-607]" ]
  }, {
    "corrective_change" : false,
    "events" : [ {
      "new_value" : "m",
      "corrective_change" : false,
      "property" : "nyjomy",
      "name" : "rilaxe",
      "old_value" : "M",
      "status" : "success",
      "timestamp" : "2023-07-19T02:19:54.375Z",
      "message" : "Dakytynuta m rovig xereripini mec."
    } ],
    "file" : "GSzgQeT",
    "skipped" : false,
    "line" : 155,
    "resource_type" : "Exec",
    "resource_title" : "resource-lazaquqehyzucykytawocujyxalub-635",
    "timestamp" : "2023-07-19T02:19:54.337Z",
    "containment_path" : [ "Stage[main]", "Class[class-zaqekahudybepesizakanihoqusuqozih-94]", "Exec[resource-lazaquqehyzucykytawocujyxalub-635]" ]
  }, {
    "corrective_change" : false,
    "events" : [ {
      "new_value" : "YMAhSDGZMSLIVyFqtzYlEMIcXwumB",
      "corrective_change" : false,
      "property" : "petuve",
      "name" : "wy_zoby",
      "old_value" : "LiVuidcpZEFdIiqPflLNdUVvTNsAD",
      "status" : "success",
      "timestamp" : "2023-07-19T02:19:54.463Z",
      "message" : "xMlUXnhnYgsWSnSZICbcDnClXvgSh"
    } ],
    "file" : "t",
    "skipped" : false,
    "line" : 869,
    "resource_type" : "Service",
    "resource_title" : "resource-bicyrurypobasemycagiqiwyjogoz-644",
    "timestamp" : "2023-07-19T02:19:54.461Z",
    "containment_path" : [ "Stage[main]", "Class[class-lypimubytusozumuhehikehewyjunotul-27]", "Service[resource-bicyrurypobasemycagiqiwyjogoz-644]" ]
  }, {
    "corrective_change" : false,
    "events" : [ {
      "new_value" : "aGX",
      "corrective_change" : false,
      "property" : "mucyde",
      "name" : "gulodo",
      "old_value" : "lPb",
      "status" : "success",
      "timestamp" : "2023-07-19T02:19:54.586Z",
      "message" : "Pi pesiwucox nubocexu gifak loq."
    } ],
    "file" : "Sx",
    "skipped" : false,
    "line" : 228,
    "resource_type" : "User",
    "resource_title" : "resource-kugewikuhedicuboqucoxeduvuheg-697",
    "timestamp" : "2023-07-19T02:19:54.546Z",
    "containment_path" : [ "Stage[main]", "Class[class-fiqiwevemalucyqoxygejimukuberolum-44]", "User[resource-kugewikuhedicuboqucoxeduvuheg-697]" ]
  } ],
  "noop_pending" : false,
  "certname" : "host-tynahu-1",
  "metrics" : [ {
    "name" : "changed",
    "value" : 0,
    "category" : "resources"
  }, {
    "name" : "corrective_change",
    "value" : 0,
    "category" : "resources"
  }, {
    "name" : "failed",
    "value" : 0,
    "category" : "resources"
  }, {
    "name" : "failed_to_restart",
    "value" : 0,
    "category" : "resources"
  }, {
    "name" : "out_of_sync",
    "value" : 0,
    "category" : "resources"
  }, {
    "name" : "restarted",
    "value" : 0,
    "category" : "resources"
  }, {
    "name" : "scheduled",
    "value" : 0,
    "category" : "resources"
  }, {
    "name" : "skipped",
    "value" : 0,
    "category" : "resources"
  }, {
    "name" : "zipawojuwyviwiriq",
    "value" : 0.31017446517944336,
    "category" : "times"
  }, {
    "name" : "lezyn",
    "value" : 0.6654391288757324,
    "category" : "times"
  }, {
    "name" : "vewoqicofygaz",
    "value" : 0.8483599424362183,
    "category" : "times"
  }, {
    "name" : "jogan",
    "value" : 0.13164985179901123,
    "category" : "times"
  }, {
    "name" : "fuxacupydyqok",
    "value" : 0.6074884533882141,
    "category" : "times"
  }, {
    "name" : "tymiq",
    "value" : 0.6648999452590942,
    "category" : "times"
  }, {
    "name" : "nucilasitymy",
    "value" : 38.25115126371384,
    "category" : "times"
  }, {
    "name" : "japovugawagaref",
    "value" : 0.8753634691238403,
    "category" : "times"
  }, {
    "name" : "quriniv",
    "value" : 10.125225245952606,
    "category" : "times"
  }, {
    "name" : "duqejot",
    "value" : 0.6665509939193726,
    "category" : "times"
  }, {
    "name" : "cewibiseno",
    "value" : 0.08162689208984375,
    "category" : "times"
  }, {
    "name" : "zihosovakiwijeqype",
    "value" : 0.5208886861801147,
    "category" : "times"
  }, {
    "name" : "lyjykifimovozu",
    "value" : 4.926743805408478,
    "category" : "times"
  }, {
    "name" : "fytipydynuj",
    "value" : 0.775885283946991,
    "category" : "times"
  }, {
    "name" : "lujovagebexa",
    "value" : 1.7925173044204712,
    "category" : "times"
  }, {
    "name" : "suf",
    "value" : 0.5035505294799805,
    "category" : "times"
  }, {
    "name" : "xovug",
    "value" : 0.6267073154449463,
    "category" : "times"
  }, {
    "name" : "jalup",
    "value" : 24.242417693138123,
    "category" : "times"
  }, {
    "name" : "package",
    "value" : 0.2861461639404297,
    "category" : "times"
  }, {
    "name" : "bavosohelixunu",
    "value" : 0.37535905838012695,
    "category" : "times"
  }, {
    "name" : "xuvasacefeto",
    "value" : 0.9781056642532349,
    "category" : "times"
  }, {
    "name" : "dexisygu",
    "value" : 0.697521984577179,
    "category" : "times"
  }, {
    "name" : "wawypes",
    "value" : 0.8724452257156372,
    "category" : "times"
  }, {
    "name" : "sadetokah",
    "value" : 0.61716628074646,
    "category" : "times"
  }, {
    "name" : "fofukydalodo",
    "value" : 25.129524767398834,
    "category" : "times"
  }, {
    "name" : "banabu",
    "value" : 0.6106719374656677,
    "category" : "times"
  }, {
    "name" : "ludugadyj",
    "value" : 9.689329862594604,
    "category" : "times"
  }, {
    "name" : "pequfynyfajytut",
    "value" : 0.09231585264205933,
    "category" : "times"
  }, {
    "name" : "dunitohyb",
    "value" : 1.3798017501831055,
    "category" : "times"
  }, {
    "name" : "witytexetiqafipan",
    "value" : 0.12550395727157593,
    "category" : "times"
  }, {
    "name" : "repakejynocoh",
    "value" : 0.8164488673210144,
    "category" : "times"
  }, {
    "name" : "wapubalywad",
    "value" : 0.3121543526649475,
    "category" : "times"
  }, {
    "name" : "rotyqusumusizovizofi",
    "value" : 0.6660096645355225,
    "category" : "times"
  }, {
    "name" : "ro",
    "value" : 0.9810675978660583,
    "category" : "times"
  }, {
    "name" : "fukafuf",
    "value" : 0.4595176577568054,
    "category" : "times"
  }, {
    "name" : "hezecyreno",
    "value" : 0.29019129276275635,
    "category" : "times"
  }, {
    "name" : "tujyfawif",
    "value" : 0.9426381587982178,
    "category" : "times"
  }, {
    "name" : "pe",
    "value" : 0.08026391267776489,
    "category" : "times"
  }, {
    "name" : "kizavonomum",
    "value" : 0.5117868781089783,
    "category" : "times"
  }, {
    "name" : "qavuwo",
    "value" : 0.05433303117752075,
    "category" : "times"
  }, {
    "name" : "hixoruqehyxeqoly",
    "value" : 0.4247680902481079,
    "category" : "times"
  }, {
    "name" : "bejalodilyfuhih",
    "value" : 11.195574223995209,
    "category" : "times"
  }, {
    "name" : "vaka",
    "value" : 0.8524987697601318,
    "category" : "times"
  }, {
    "name" : "musaqyrabet",
    "value" : 2.55394583940506,
    "category" : "times"
  }, {
    "name" : "cehykasan",
    "value" : 0.9902294874191284,
    "category" : "times"
  }, {
    "name" : "class",
    "value" : 0.482424259185791,
    "category" : "times"
  }, {
    "name" : "kadogod",
    "value" : 0.619645893573761,
    "category" : "times"
  }, {
    "name" : "zivalawiw",
    "value" : 0.47588276863098145,
    "category" : "times"
  }, {
    "name" : "zipofybyqetu",
    "value" : 0.9638230204582214,
    "category" : "times"
  }, {
    "name" : "wucipoqyzaba",
    "value" : 2.7554430961608887,
    "category" : "times"
  }, {
    "name" : "jawynila",
    "value" : 0.7055350542068481,
    "category" : "times"
  }, {
    "name" : "remygyqyhumol",
    "value" : 0.4032595753669739,
    "category" : "times"
  }, {
    "name" : "user",
    "value" : 0.8736769556999207,
    "category" : "times"
  }, {
    "name" : "xajyse",
    "value" : 0.6468822360038757,
    "category" : "times"
  }, {
    "name" : "qy",
    "value" : 0.03751933574676514,
    "category" : "times"
  }, {
    "name" : "dow",
    "value" : 0.39178985357284546,
    "category" : "times"
  }, {
    "name" : "gavigovoga",
    "value" : 0.39309173822402954,
    "category" : "times"
  }, {
    "name" : "hepiwymuhisomyhob",
    "value" : 0.7558443546295166,
    "category" : "times"
  }, {
    "name" : "belyryv",
    "value" : 0.10112017393112183,
    "category" : "times"
  }, {
    "name" : "mejenimysyvyv",
    "value" : 0.7768679261207581,
    "category" : "times"
  }, {
    "name" : "sevafimuhod",
    "value" : 0.6125481128692627,
    "category" : "times"
  }, {
    "name" : "hydykyn",
    "value" : 0.07989645004272461,
    "category" : "times"
  }, {
    "name" : "wejusy",
    "value" : 0.2763017416000366,
    "category" : "times"
  }, {
    "name" : "qifojemycijevek",
    "value" : 4.283164381980896,
    "category" : "times"
  }, {
    "name" : "rirufizifivary",
    "value" : 0.5620560646057129,
    "category" : "times"
  }, {
    "name" : "sikisomalecopo",
    "value" : 0.43715041875839233,
    "category" : "times"
  }, {
    "name" : "hahyjafeza",
    "value" : 12.136967182159424,
    "category" : "times"
  }, {
    "name" : "rihihovema",
    "value" : 0.0070111751556396484,
    "category" : "times"
  }, {
    "name" : "ly",
    "value" : 0.7942079305648804,
    "category" : "times"
  }, {
    "name" : "nyqawypekuwihu",
    "value" : 0.19889724254608154,
    "category" : "times"
  }, {
    "name" : "cobelixud",
    "value" : 0.015252172946929932,
    "category" : "times"
  }, {
    "name" : "exec",
    "value" : 0.846889078617096,
    "category" : "times"
  }, {
    "name" : "himykahy",
    "value" : 42.09805375337601,
    "category" : "times"
  }, {
    "name" : "risijinohezuso",
    "value" : 0.5941691994667053,
    "category" : "times"
  }, {
    "name" : "qalywovunuv",
    "value" : 0.07172590494155884,
    "category" : "times"
  }, {
    "name" : "ponynodemedeva",
    "value" : 0.5323793888092041,
    "category" : "times"
  }, {
    "name" : "wyxifofima",
    "value" : 0.53249591588974,
    "category" : "times"
  }, {
    "name" : "fevolafo",
    "value" : 0.6738409996032715,
    "category" : "times"
  }, {
    "name" : "wobysapijusu",
    "value" : 0.41536229848861694,
    "category" : "times"
  }, {
    "name" : "sijuc",
    "value" : 0.6573451161384583,
    "category" : "times"
  }, {
    "name" : "wu",
    "value" : 0.9189398288726807,
    "category" : "times"
  }, {
    "name" : "novemecyfylid",
    "value" : 0.9606051445007324,
    "category" : "times"
  }, {
    "name" : "bufafenyzehufyryt",
    "value" : 0.6676884889602661,
    "category" : "times"
  }, {
    "name" : "rahyfokeduzapalivib",
    "value" : 0.4661000370979309,
    "category" : "times"
  }, {
    "name" : "qovaqyd",
    "value" : 0.42444002628326416,
    "category" : "times"
  }, {
    "name" : "wolirij",
    "value" : 18.01178354024887,
    "category" : "times"
  }, {
    "name" : "qezomesiv",
    "value" : 0.8077977299690247,
    "category" : "times"
  }, {
    "name" : "xegifezuz",
    "value" : 0.5259991884231567,
    "category" : "times"
  }, {
    "name" : "terysumaxydakyvev",
    "value" : 0.5909374356269836,
    "category" : "times"
  }, {
    "name" : "wiwonadaca",
    "value" : 0.9057545065879822,
    "category" : "times"
  }, {
    "name" : "qefegygopahaludo",
    "value" : 14.322249233722687,
    "category" : "times"
  }, {
    "name" : "rimaqitadug",
    "value" : 0.5972285270690918,
    "category" : "times"
  }, {
    "name" : "veqacuficuxykod",
    "value" : 0.050141990184783936,
    "category" : "times"
  }, {
    "name" : "jacosolygony",
    "value" : 0.7729465961456299,
    "category" : "times"
  }, {
    "name" : "zudugezudyzorelu",
    "value" : 0.1289648413658142,
    "category" : "times"
  }, {
    "name" : "wyvetabuwoc",
    "value" : 0.7784262895584106,
    "category" : "times"
  }, {
    "name" : "sefajisesupohus",
    "value" : 0.6183164715766907,
    "category" : "times"
  }, {
    "name" : "tuguky",
    "value" : 0.343916654586792,
    "category" : "times"
  }, {
    "name" : "zybizaxekeqa",
    "value" : 39.569143176078796,
    "category" : "times"
  }, {
    "name" : "goqito",
    "value" : 12.459867000579834,
    "category" : "times"
  }, {
    "name" : "dig",
    "value" : 0.6361654996871948,
    "category" : "times"
  }, {
    "name" : "qovahok",
    "value" : 0.41690486669540405,
    "category" : "times"
  }, {
    "name" : "kunuve",
    "value" : 0.9473857879638672,
    "category" : "times"
  }, {
    "name" : "waviqymy",
    "value" : 0.39588189125061035,
    "category" : "times"
  }, {
    "name" : "rakitetusyricy",
    "value" : 0.4361109733581543,
    "category" : "times"
  }, {
    "name" : "panoqanyfaw",
    "value" : 0.6642299890518188,
    "category" : "times"
  }, {
    "name" : "joxusa",
    "value" : 0.7384952902793884,
    "category" : "times"
  }, {
    "name" : "cikuzapewizajegut",
    "value" : 0.7534494400024414,
    "category" : "times"
  }, {
    "name" : "qilabykosy",
    "value" : 0.04670339822769165,
    "category" : "times"
  }, {
    "name" : "pawaxyt",
    "value" : 0.23162156343460083,
    "category" : "times"
  }, {
    "name" : "rukinise",
    "value" : 0.11995142698287964,
    "category" : "times"
  }, {
    "name" : "rucedevokytoc",
    "value" : 0.7898236513137817,
    "category" : "times"
  }, {
    "name" : "dahusa",
    "value" : 0.5304046273231506,
    "category" : "times"
  }, {
    "name" : "file",
    "value" : 0.7396185994148254,
    "category" : "times"
  }, {
    "name" : "ny",
    "value" : 0.9914700984954834,
    "category" : "times"
  }, {
    "name" : "zovolag",
    "value" : 0.6408967971801758,
    "category" : "times"
  }, {
    "name" : "citekeqy",
    "value" : 15.279495000839233,
    "category" : "times"
  }, {
    "name" : "rijarakotibefoxe",
    "value" : 0.09591233730316162,
    "category" : "times"
  }, {
    "name" : "service",
    "value" : 0.026249051094055176,
    "category" : "times"
  }, {
    "name" : "xesijyramo",
    "value" : 0.8928261995315552,
    "category" : "times"
  }, {
    "name" : "wynadilyp",
    "value" : 0.7327849864959717,
    "category" : "times"
  }, {
    "name" : "petamepygi",
    "value" : 0.6682602167129517,
    "category" : "times"
  }, {
    "name" : "vesoqeca",
    "value" : 0.5908190608024597,
    "category" : "times"
  }, {
    "name" : "wexenu",
    "value" : 0.2882581353187561,
    "category" : "times"
  }, {
    "name" : "padoluxowah",
    "value" : 0.12491011619567871,
    "category" : "times"
  }, {
    "name" : "gyhoxanuduteli",
    "value" : 0.9675187468528748,
    "category" : "times"
  }, {
    "name" : "bemeqabux",
    "value" : 0.9595506191253662,
    "category" : "times"
  }, {
    "name" : "jibuhefe",
    "value" : 0.2581176161766052,
    "category" : "times"
  }, {
    "name" : "pur",
    "value" : 0.32638633251190186,
    "category" : "times"
  }, {
    "name" : "gynosazalukujuhaci",
    "value" : 0.8394650220870972,
    "category" : "times"
  }, {
    "name" : "hixijom",
    "value" : 0.13288187980651855,
    "category" : "times"
  }, {
    "name" : "bamabynagy",
    "value" : 43.440120220184326,
    "category" : "times"
  }, {
    "name" : "sehepami",
    "value" : 22.596812784671783,
    "category" : "times"
  }, {
    "name" : "zoreguc",
    "value" : 0.9743250012397766,
    "category" : "times"
  }, {
    "name" : "jinajore",
    "value" : 25.601674675941467,
    "category" : "times"
  }, {
    "name" : "vizybyre",
    "value" : 0.9625070691108704,
    "category" : "times"
  }, {
    "name" : "kylyhezobufuk",
    "value" : 0.16051363945007324,
    "category" : "times"
  }, {
    "name" : "jiqasavazy",
    "value" : 0.19807982444763184,
    "category" : "times"
  }, {
    "name" : "stage",
    "value" : 0.549604058265686,
    "category" : "times"
  }, {
    "name" : "total",
    "value" : 40,
    "category" : "changes"
  }, {
    "name" : "failure",
    "value" : 0,
    "category" : "events"
  }, {
    "name" : "success",
    "value" : 40,
    "category" : "events"
  }, {
    "name" : "total",
    "value" : 40,
    "category" : "events"
  } ],
  "job_id" : null
}